psychopy_scene/__init__.py
psychopy_scene-0.2.0.dist-info/licenses/LICENSE
psychopy_scene-0.2.0.dist-info/METADATA
psychopy_scene-0.2.0.dist-info/WHEEL
psychopy_scene-0.2.0.dist-info/top_level.txt
psychopy_scene-0.2.0.dist-info/RECORD
