Metadata-Version: 2.4
Name: psychopy-scene
Version: 0.2.0
Summary: Lightweight framework for PsychoPy
Author-email: cubx <shawn6304@qq.com>
Project-URL: repository, https://github.com/bluebonesx/psychopy-scene
Classifier: Programming Language :: Python :: 3.8
Classifier: Operating System :: OS Independent
Classifier: Topic :: Scientific/Engineering
Classifier: License :: OSI Approved :: GNU General Public License v3 or later (GPLv3+)
Requires-Python: >=3.8
License-File: LICENSE
Requires-Dist: psychopy
Provides-Extra: type-hints
Requires-Dist: typing_extensions; extra == "type-hints"
Dynamic: license-file
